lidlplus/__init__.py
lidlplus/__main__.py
lidlplus/api.py
lidlplus/exceptions.py
lidl_plus-0.3.5.dist-info/LICENCE
lidl_plus-0.3.5.dist-info/METADATA
lidl_plus-0.3.5.dist-info/WHEEL
lidl_plus-0.3.5.dist-info/entry_points.txt
lidl_plus-0.3.5.dist-info/top_level.txt
lidl_plus-0.3.5.dist-info/RECORD
