Metadata-Version: 2.1
Name: lidl-plus
Version: 0.3.5
Summary: Fetch receipts and more from Lidl Plus
Author: Andre Basche
License: MIT
Project-URL: GitHub, https://github.com/Andre0512/lidl-plus
Project-URL: PyPI, https://pypi.org/project/lidl-plus/
Platform: any
Classifier: Development Status :: 4 - Beta
Classifier: Environment :: Console
Classifier: License :: OSI Approved :: MIT License
Classifier: Natural Language :: English
Classifier: Operating System :: OS Independent
Classifier: Programming Language :: Python :: 3.8
Classifier: Programming Language :: Python :: 3.9
Classifier: Programming Language :: Python :: 3.10
Classifier: Programming Language :: Python :: 3.11
Classifier: Programming Language :: Python :: 3.12
Classifier: Topic :: Software Development :: Libraries :: Python Modules
Requires-Python: >=3.8
License-File: LICENCE
Requires-Dist: requests >=2.28.1
Provides-Extra: auth
Requires-Dist: getuseragent >=0.0.7 ; extra == 'auth'
Requires-Dist: oic >=1.4.0 ; extra == 'auth'
Requires-Dist: selenium-wire >=5.1.0 ; extra == 'auth'
Requires-Dist: webdriver-manager >=3.8.5 ; extra == 'auth'
